mixtiles_mobileclip/__init__.py
mixtiles_mobileclip/clip.py
mixtiles_mobileclip/image_encoder.py
mixtiles_mobileclip/logger.py
mixtiles_mobileclip/text_encoder.py
mixtiles_mobileclip/configs/mobileclip_b.json
mixtiles_mobileclip/configs/mobileclip_s0.json
mixtiles_mobileclip/configs/mobileclip_s1.json
mixtiles_mobileclip/configs/mobileclip_s2.json
mixtiles_mobileclip/models/__init__.py
mixtiles_mobileclip/models/mci.py
mixtiles_mobileclip/models/vit.py
mixtiles_mobileclip/modules/__init__.py
mixtiles_mobileclip/modules/common/__init__.py
mixtiles_mobileclip/modules/common/mobileone.py
mixtiles_mobileclip/modules/common/transformer.py
mixtiles_mobileclip/modules/image/__init__.py
mixtiles_mobileclip/modules/image/image_projection.py
mixtiles_mobileclip/modules/image/replknet.py
mixtiles_mobileclip/modules/text/__init__.py
mixtiles_mobileclip/modules/text/repmixer.py
mixtiles_mobileclip/modules/text/tokenizer.py
mixtiles_mobileclip-0.2.0.dist-info/METADATA
mixtiles_mobileclip-0.2.0.dist-info/WHEEL
mixtiles_mobileclip-0.2.0.dist-info/licenses/LICENSE
mixtiles_mobileclip-0.2.0.dist-info/licenses/LICENSE_weights_data
mixtiles_mobileclip-0.2.0.dist-info/RECORD
