Metadata-Version: 2.4
Name: mixtiles-mobileclip
Version: 0.2.0
Summary: A fork of MobileCLIP modified for Mixtile's needs
Author-email: Soof Golan <soof@mixtiles.com>
License-File: LICENSE
License-File: LICENSE_weights_data
Classifier: Development Status :: 3 - Alpha
Classifier: Intended Audience :: Education
Classifier: Intended Audience :: Science/Research
Classifier: Programming Language :: Python :: 3.10
Classifier: Programming Language :: Python :: 3.11
Classifier: Programming Language :: Python :: 3.12
Classifier: Programming Language :: Python :: 3.13
Classifier: Topic :: Scientific/Engineering
Classifier: Topic :: Scientific/Engineering :: Artificial Intelligence
Classifier: Topic :: Software Development
Classifier: Topic :: Software Development :: Libraries
Classifier: Topic :: Software Development :: Libraries :: Python Modules
Requires-Python: >=3.10
Requires-Dist: open-clip-torch>=2.20.0
Requires-Dist: timm>=0.9.5
Requires-Dist: torch>=2.1.0
Requires-Dist: torchvision>=0.20.1
